<?xml version="1.0" encoding="utf-8" ?>
<dwsync>
<file name="ribbonblue.png" server="moodle-test.warwick.ac.uk//data/www/html/" local="130417063307635197" remote="130460233920000000" />
<file name="Desert.jpg" server="moodle-test.warwick.ac.uk//data/www/html/" local="128920231510000000" remote="130460233890000000" />
<file name="moodle-ladders.jpg" server="moodle-test.warwick.ac.uk//data/www/html/" local="130429950100000000" remote="130460233900000000" />
<file name="ribbongreen.png" server="moodle-test.warwick.ac.uk//data/www/html/" local="130447215900000000" remote="130460233920000000" />
<file name="ribbonred.png" server="moodle-test.warwick.ac.uk//data/www/html/" local="130447218690000000" remote="130460233920000000" />
<file name="ribbonorange.png" server="moodle-test.warwick.ac.uk//data/www/html/" local="130447232110000000" remote="130460233920000000" />
<file name="ribbongrey.png" server="moodle-test.warwick.ac.uk//data/www/html/" local="130447252880000000" remote="130460233920000000" />
<file name="moodle-ladders-old.jpg" server="moodle-test.warwick.ac.uk//data/www/html/" local="130427391580000000" remote="130460233900000000" />
<file name="tiny_trans.png" server="moodle-test.warwick.ac.uk//data/www/html/" local="130452465530000000" remote="130460233930000000" />
<file name="large_img_placeholder.jpg" server="moodle-test.warwick.ac.uk//data/www/html/" local="130457657520000000" remote="130460233890000000" />
<file name="small_img_placeholder230w173h.jpg" server="moodle-test.warwick.ac.uk//data/www/html/" local="130460244771907987" remote="130460244970000000" />
<file name="small_img_placeholder200w150h.jpg" server="moodle-test.warwick.ac.uk//data/www/html/" local="130460259978187737" remote="130460260160000000" />
</dwsync>